melexis/i2c_stick/I2CStick.py
melexis/i2c_stick/MemoryFile.py
melexis/i2c_stick/__init__.py
melexis/i2c_stick/__main__.py
melexis_i2c_stick-1.6.0.dist-info/licenses/LICENSE
melexis_i2c_stick-1.6.0.dist-info/licenses/NOTICE
melexis_i2c_stick-1.6.0.dist-info/METADATA
melexis_i2c_stick-1.6.0.dist-info/WHEEL
melexis_i2c_stick-1.6.0.dist-info/entry_points.txt
melexis_i2c_stick-1.6.0.dist-info/top_level.txt
melexis_i2c_stick-1.6.0.dist-info/RECORD
