Metadata-Version: 2.4
Name: melexis-i2c-stick
Version: 1.6.0
Summary: Melexis I2C Stick, python interface
Author-email: Karel Vanroye <kva@melexis.com>
License:    Copyright 2023 Melexis
Project-URL: Homepage, https://github.com/melexis/i2c-stick
Keywords: Melexis,I2C,sensors,demo
Classifier: License :: OSI Approved :: Apache Software License
Classifier: Programming Language :: Python
Classifier: Programming Language :: Python :: 3
Requires-Python: >=3.3
License-File: LICENSE
License-File: NOTICE
Requires-Dist: bincopy>=18
Requires-Dist: pyserial>=3.5
Provides-Extra: dev
Dynamic: license-file
